pdftools_toolbox/__init__.py
pdftools_toolbox/conformance_error.py
pdftools_toolbox/corrupt_error.py
pdftools_toolbox/exists_error.py
pdftools_toolbox/generic_error.py
pdftools_toolbox/http_error.py
pdftools_toolbox/license_error.py
pdftools_toolbox/not_found_error.py
pdftools_toolbox/operation_error.py
pdftools_toolbox/password_error.py
pdftools_toolbox/sdk.py
pdftools_toolbox/state_error.py
pdftools_toolbox/string_map.py
pdftools_toolbox/unknown_format_error.py
pdftools_toolbox/unsupported_feature_error.py
pdftools_toolbox/geometry/__init__.py
pdftools_toolbox/geometry/horizontal_alignment.py
pdftools_toolbox/geometry/rotation.py
pdftools_toolbox/geometry/integer/__init__.py
pdftools_toolbox/geometry/integer/size.py
pdftools_toolbox/geometry/real/__init__.py
pdftools_toolbox/geometry/real/affine_transform.py
pdftools_toolbox/geometry/real/point.py
pdftools_toolbox/geometry/real/quadrilateral.py
pdftools_toolbox/geometry/real/quadrilateral_list.py
pdftools_toolbox/geometry/real/rectangle.py
pdftools_toolbox/geometry/real/size.py
pdftools_toolbox/internal/__init__.py
pdftools_toolbox/internal/native_base.py
pdftools_toolbox/internal/native_object.py
pdftools_toolbox/internal/streams.py
pdftools_toolbox/internal/utils.py
pdftools_toolbox/lib/linux-arm64/libPdfTools_Toolbox.so
pdftools_toolbox/lib/linux-x64/libPdfTools_Toolbox.so
pdftools_toolbox/lib/osx-arm64/libPdfTools_Toolbox.dylib
pdftools_toolbox/lib/osx-x64/libPdfTools_Toolbox.dylib
pdftools_toolbox/lib/win-arm64/PdfTools_Toolbox.dll
pdftools_toolbox/lib/win-x64/PdfTools_Toolbox.dll
pdftools_toolbox/lib/win-x86/PdfTools_Toolbox.dll
pdftools_toolbox/pdf/__init__.py
pdftools_toolbox/pdf/conformance.py
pdftools_toolbox/pdf/copy_strategy.py
pdftools_toolbox/pdf/document.py
pdftools_toolbox/pdf/encryption.py
pdftools_toolbox/pdf/file_reference.py
pdftools_toolbox/pdf/file_reference_list.py
pdftools_toolbox/pdf/metadata.py
pdftools_toolbox/pdf/name_conflict_resolution.py
pdftools_toolbox/pdf/ocg_state.py
pdftools_toolbox-1.10.0.dist-info/METADATA
pdftools_toolbox-1.10.0.dist-info/WHEEL
pdftools_toolbox-1.10.0.dist-info/top_level.txt
pdftools_toolbox-1.10.0.dist-info/RECORD
