Metadata-Version: 2.1
Name: pdftools-toolbox
Version: 1.10.0
Summary: Python package for Pdftools Toolbox
Home-page: https://www.pdf-tools.com/products/conversion/pdf-tools-sdk/?utm_medium=repository&utm_source=pypi&utm_campaign=pdftoolssdk
Author: PDF Tools AG
License: Proprietary
Project-URL: Documentation, https://www.pdf-tools.com/docs/pdf-tools-sdk
Project-URL: Support, https://www.pdf-tools.com/docs/support/
Project-URL: Contact, https://www.pdf-tools.com/contact/
Platform: UNKNOWN
Classifier: Development Status :: 5 - Production/Stable
Classifier: Intended Audience :: Developers
Classifier: Topic :: Software Development :: Libraries
Classifier: Topic :: Software Development :: Libraries :: Python Modules
Classifier: Programming Language :: Python :: 3.7
Classifier: Programming Language :: Python :: 3.8
Classifier: Programming Language :: Python :: 3.9
Classifier: Programming Language :: Python :: 3.10
Classifier: License :: Other/Proprietary License
Classifier: Operating System :: MacOS
Classifier: Operating System :: Microsoft :: Windows
Classifier: Operating System :: POSIX :: Linux
Requires-Python: >=3.7
License-File: pdf-tools-license.md
